{
  "templo": 35,
  "nome": "L'Ambiente e l'Ecologia",
  "cidade": "Torino",
  "nivel": "B1",
  "palavras": [
    {
      "id": "t35_012",
      "italiano": "animale",
      "portugues": "animal",
      "genero": "m",
      "plural": "animali",
      "exemplo": "Un animale selvatico.",
      "exemplo_pt": "Um animal selvagem.",
      "categoria": "natura",
      "dificuldade": "medio",
      "audio_ipa": "/aniˈmale/"
    },
    {
      "id": "t35_014",
      "italiano": "ecosistema",
      "portugues": "ecossistema",
      "genero": "m",
      "plural": "ecosistemi",
      "exemplo": "L'equilibrio dell'ecosistema.",
      "exemplo_pt": "O equilíbrio do ecossistema.",
      "categoria": "natura",
      "dificuldade": "medio",
      "audio_ipa": "/ekosisˈtɛma/"
    },
    {
      "id": "t35_017",
      "italiano": "suolo",
      "portugues": "solo",
      "genero": "m",
      "plural": "suoli",
      "exemplo": "Inquinamento del suolo.",
      "exemplo_pt": "Poluição do solo.",
      "categoria": "natura",
      "dificuldade": "medio",
      "audio_ipa": "/ˈswɔlo/"
    },
    {
      "id": "t35_020",
      "italiano": "rifiuto",
      "portugues": "lixo/resíduo",
      "genero": "m",
      "plural": "rifiuti",
      "exemplo": "I rifiuti tossici.",
      "exemplo_pt": "Os resíduos tóxicos.",
      "categoria": "problemi",
      "dificuldade": "medio",
      "audio_ipa": "/riˈfjuto/"
    },
    {
      "id": "t35_021",
      "italiano": "spazzatura",
      "portugues": "lixo",
      "genero": "f",
      "plural": "spazzature",
      "exemplo": "Buttare la spazzatura.",
      "exemplo_pt": "Jogar o lixo.",
      "categoria": "problemi",
      "dificuldade": "medio",
      "audio_ipa": "/spattsaˈtura/"
    },
    {
      "id": "t35_023",
      "italiano": "plastica",
      "portugues": "plástico",
      "genero": "f",
      "plural": "plastiche",
      "exemplo": "Troppa plastica in mare.",
      "exemplo_pt": "Muito plástico no mar.",
      "categoria": "problemi",
      "dificuldade": "medio",
      "audio_ipa": "/ˈplastika/"
    },
    {
      "id": "t35_024",
      "italiano": "smog",
      "portugues": "poluição (ar)",
      "genero": "m",
      "plural": "smog",
      "exemplo": "C'è molto smog in città.",
      "exemplo_pt": "Tem muita poluição na cidade.",
      "categoria": "problemi",
      "dificuldade": "medio",
      "audio_ipa": "/zmɔɡ/"
    },
    {
      "id": "t35_025",
      "italiano": "emissione",
      "portugues": "emissão",
      "genero": "f",
      "plural": "emissioni",
      "exemplo": "Le emissioni di gas.",
      "exemplo_pt": "As emissões de gás.",
      "categoria": "problemi",
      "dificuldade": "medio",
      "audio_ipa": "/emisˈsjone/"
    },
    {
      "id": "t35_026",
      "italiano": "gas serra",
      "portugues": "gás de efeito estufa",
      "genero": "m",
      "plural": "gas serra",
      "exemplo": "I gas serra aumentano.",
      "exemplo_pt": "Os gases de efeito estufa aumentam.",
      "categoria": "problemi",
      "dificuldade": "medio",
      "audio_ipa": "/ɡas ˈsɛrra/"
    },
    {
      "id": "t35_028",
      "italiano": "disboscamento",
      "portugues": "desmatamento",
      "genero": "m",
      "plural": "disboscamenti",
      "exemplo": "Il disboscamento è grave.",
      "exemplo_pt": "O desmatamento é grave.",
      "categoria": "problemi",
      "dificuldade": "medio",
      "audio_ipa": "/dizboskaˈmento/"
    },
    {
      "id": "t35_031",
      "italiano": "degrado",
      "portugues": "degradação",
      "genero": "m",
      "plural": "degradi",
      "exemplo": "Il degrado ambientale.",
      "exemplo_pt": "A degradação ambiental.",
      "categoria": "problemi",
      "dificuldade": "medio",
      "audio_ipa": "/deˈɡrado/"
    },
    {
      "id": "t35_032",
      "italiano": "disastro",
      "portugues": "desastre",
      "genero": "m",
      "plural": "disastri",
      "exemplo": "Un disastro naturale.",
      "exemplo_pt": "Um desastre natural.",
      "categoria": "problemi",
      "dificuldade": "medio",
      "audio_ipa": "/diˈzastro/"
    },
    {
      "id": "t35_033",
      "italiano": "spreco",
      "portugues": "desperdício",
      "genero": "m",
      "plural": "spree",
      "exemplo": "Evitare lo spreco d'acqua.",
      "exemplo_pt": "Evitar o desperdício de água.",
      "categoria": "problemi",
      "dificuldade": "medio",
      "audio_ipa": "/ˈsprɛko/"
    },
    {
      "id": "t35_034",
      "italiano": "estinzione",
      "portugues": "extinção",
      "genero": "f",
      "plural": "estinzioni",
      "exemplo": "Specie a rischio di estinzione.",
      "exemplo_pt": "Espécie em risco de extinção.",
      "categoria": "problemi",
      "dificuldade": "medio",
      "audio_ipa": "/estinˈtsjone/"
    },
    {
      "id": "t35_035",
      "italiano": "pesticida",
      "portugues": "agrotóxico",
      "genero": "m",
      "plural": "pesticidi",
      "exemplo": "L'uso di pesticidi.",
      "exemplo_pt": "O uso de agrotóxicos.",
      "categoria": "problemi",
      "dificuldade": "medio",
      "audio_ipa": "/pestiˈtʃida/"
    },
    {
      "id": "t35_036",
      "italiano": "discarica",
      "portugues": "aterro sanitário",
      "genero": "f",
      "plural": "discariche",
      "exemplo": "La discarica è piena.",
      "exemplo_pt": "O aterro está cheio.",
      "categoria": "problemi",
      "dificuldade": "medio",
      "audio_ipa": "/disˈkarika/"
    },
    {
      "id": "t35_038",
      "italiano": "raccolta",
      "portugues": "coleta",
      "genero": "f",
      "plural": "raccolte",
      "exemplo": "La raccolta differenziata.",
      "exemplo_pt": "A coleta seletiva.",
      "categoria": "soluzioni",
      "dificuldade": "medio",
      "audio_ipa": "/rakˈkɔlta/"
    },
    {
      "id": "t35_040",
      "italiano": "solare",
      "portugues": "solar",
      "genero": "m",
      "plural": "solari",
      "exemplo": "Il pannello solare.",
      "exemplo_pt": "O painel solar.",
      "categoria": "soluzioni",
      "dificuldade": "medio",
      "audio_ipa": "/soˈlare/"
    },
    {
      "id": "t35_041",
      "italiano": "eolico",
      "portugues": "eólico",
      "genero": "m",
      "plural": "eolici",
      "exemplo": "Energia eolica.",
      "exemplo_pt": "Energia eólica.",
      "categoria": "soluzioni",
      "dificuldade": "medio",
      "audio_ipa": "/eˈɔliko/"
    },
    {
      "id": "t35_042",
      "italiano": "rinnovabile",
      "portugues": "renovável",
      "genero": "f",
      "plural": "rinnovabili",
      "exemplo": "Risorse rinnovabili.",
      "exemplo_pt": "Recursos renováveis.",
      "categoria": "soluzioni",
      "dificuldade": "medio",
      "audio_ipa": "/rinnoˈvabile/"
    },
    {
      "id": "t35_043",
      "italiano": "sostenibilità",
      "portugues": "sustentabilidade",
      "genero": "f",
      "plural": "sostenibilità",
      "exemplo": "La sostenibilità ambientale.",
      "exemplo_pt": "A sustentabilidade ambiental.",
      "categoria": "soluzioni",
      "dificuldade": "medio",
      "audio_ipa": "/sostenibiliˈta/"
    },
    {
      "id": "t35_045",
      "italiano": "tutela",
      "portugues": "tutela/proteção",
      "genero": "f",
      "plural": "tutele",
      "exemplo": "La tutela del territorio.",
      "exemplo_pt": "A tutela do território.",
      "categoria": "soluzioni",
      "dificuldade": "medio",
      "audio_ipa": "/tuˈtɛla/"
    },
    {
      "id": "t35_046",
      "italiano": "salvaguardia",
      "portugues": "salvaguarda/proteção",
      "genero": "f",
      "plural": "salvaguardie",
      "exemplo": "La salvaguardia dell'ambiente.",
      "exemplo_pt": "A proteção do meio ambiente.",
      "categoria": "soluzioni",
      "dificuldade": "medio",
      "audio_ipa": "/salvaˈɡwardja/"
    },
    {
      "id": "t35_047",
      "italiano": "riserva",
      "portugues": "reserva",
      "genero": "f",
      "plural": "riserve",
      "exemplo": "Una riserva naturale.",
      "exemplo_pt": "Uma reserva natural.",
      "categoria": "soluzioni",
      "dificuldade": "medio",
      "audio_ipa": "/riˈzɛrva/"
    },
    {
      "id": "t35_048",
      "italiano": "parco",
      "portugues": "parque",
      "genero": "m",
      "plural": "parchi",
      "exemplo": "Il parco nazionale.",
      "exemplo_pt": "O parque nacional.",
      "categoria": "soluzioni",
      "dificuldade": "medio",
      "audio_ipa": "/ˈparko/"
    },
    {
      "id": "t35_049",
      "italiano": "veicolo",
      "portugues": "veículo",
      "genero": "m",
      "plural": "veicoli",
      "exemplo": "Un veicolo elettrico.",
      "exemplo_pt": "Um veículo elétrico.",
      "categoria": "soluzioni",
      "dificuldade": "medio",
      "audio_ipa": "/veˈikolo/"
    },
    {
      "id": "t35_050",
      "italiano": "bici",
      "portugues": "bicicleta",
      "genero": "f",
      "plural": "bici",
      "exemplo": "Andare in bici.",
      "exemplo_pt": "Andar de bicicleta.",
      "categoria": "soluzioni",
      "dificuldade": "medio",
      "audio_ipa": "/ˈbitʃi/"
    },
    {
      "id": "t35_051",
      "italiano": "pannello",
      "portugues": "painel",
      "genero": "m",
      "plural": "pannelli",
      "exemplo": "Pannelli fotovoltaici.",
      "exemplo_pt": "Painéis fotovoltaicos.",
      "categoria": "soluzioni",
      "dificuldade": "medio",
      "audio_ipa": "/panˈnɛllo/"
    },
    {
      "id": "t35_052",
      "italiano": "turbina",
      "portugues": "turbina",
      "genero": "f",
      "plural": "turbine",
      "exemplo": "Una turbina eolica.",
      "exemplo_pt": "Uma turbina eólica.",
      "categoria": "soluzioni",
      "dificuldade": "medio",
      "audio_ipa": "/turˈbina/"
    },
    {
      "id": "t35_054",
      "italiano": "cassonetto",
      "portugues": "lixeira (rua)",
      "genero": "m",
      "plural": "cassonetti",
      "exemplo": "Butta nel cassonetto.",
      "exemplo_pt": "Jogue na lixeira.",
      "categoria": "soluzioni",
      "dificuldade": "medio",
      "audio_ipa": "/kassoˈnetto/"
    },
    {
      "id": "t35_058",
      "italiano": "riciclare",
      "portugues": "reciclar",
      "genero": null,
      "plural": null,
      "exemplo": "Riciclare il vetro.",
      "exemplo_pt": "Reciclar o vidro.",
      "categoria": "verbi",
      "dificuldade": "medio",
      "audio_ipa": "/ritʃiˈklare/"
    },
    {
      "id": "t35_061",
      "italiano": "consumare",
      "portugues": "consumir",
      "genero": null,
      "plural": null,
      "exemplo": "Consumare meno petrolio.",
      "exemplo_pt": "Consumir menos petróleo.",
      "categoria": "verbi",
      "dificuldade": "medio",
      "audio_ipa": "/konsuˈmare/"
    },
    {
      "id": "t35_062",
      "italiano": "ridurre",
      "portugues": "reduzir",
      "genero": null,
      "plural": null,
      "exemplo": "Ridurre le emissioni.",
      "exemplo_pt": "Reduzir as emissões.",
      "categoria": "verbi",
      "dificuldade": "medio",
      "audio_ipa": "/riˈdurre/"
    },
    {
      "id": "t35_063",
      "italiano": "riutilizzare",
      "portugues": "reutilizar",
      "genero": null,
      "plural": null,
      "exemplo": "Riutilizzare i sacchetti.",
      "exemplo_pt": "Reutilizar as sacolas.",
      "categoria": "verbi",
      "dificuldade": "medio",
      "audio_ipa": "/riutilidˈdzare/"
    },
    {
      "id": "t35_064",
      "italiano": "separare",
      "portugues": "separar",
      "genero": null,
      "plural": null,
      "exemplo": "Separare i rifiuti.",
      "exemplo_pt": "Separar o lixo.",
      "categoria": "verbi",
      "dificuldade": "medio",
      "audio_ipa": "/sepaˈrare/"
    },
    {
      "id": "t35_066",
      "italiano": "sporcare",
      "portugues": "sujar",
      "genero": null,
      "plural": null,
      "exemplo": "Non sporcare la strada.",
      "exemplo_pt": "Não sujar a rua.",
      "categoria": "verbi",
      "dificuldade": "medio",
      "audio_ipa": "/sporˈkare/"
    },
    {
      "id": "t35_070",
      "italiano": "sciogliere",
      "portugues": "derreter",
      "genero": null,
      "plural": null,
      "exemplo": "Il ghiaccio si scioglie.",
      "exemplo_pt": "O gelo derrete.",
      "categoria": "verbi",
      "dificuldade": "medio",
      "audio_ipa": "/ˈʃɔʎʎere/"
    },
    {
      "id": "t35_071",
      "italiano": "riscaldare",
      "portugues": "aquecer",
      "genero": null,
      "plural": null,
      "exemplo": "Il pianeta si riscalda.",
      "exemplo_pt": "O planeta se aquece.",
      "categoria": "verbi",
      "dificuldade": "medio",
      "audio_ipa": "/riskalˈdare/"
    },
    {
      "id": "t35_072",
      "italiano": "coltivare",
      "portugues": "cultivar",
      "genero": null,
      "plural": null,
      "exemplo": "Coltivare la terra.",
      "exemplo_pt": "Cultivar a terra.",
      "categoria": "verbi",
      "dificuldade": "medio",
      "audio_ipa": "/koltiˈvare/"
    },
    {
      "id": "t35_073",
      "italiano": "allevare",
      "portugues": "criar (animais)",
      "genero": null,
      "plural": null,
      "exemplo": "Allevare mucche.",
      "exemplo_pt": "Criar vacas.",
      "categoria": "verbi",
      "dificuldade": "medio",
      "audio_ipa": "/alleˈvare/"
    },
    {
      "id": "t35_077",
      "italiano": "sporco",
      "portugues": "sujo",
      "genero": "m",
      "plural": "sporchi",
      "exemplo": "Il fiume è sporco.",
      "exemplo_pt": "O rio está sujo.",
      "categoria": "aggettivi",
      "dificuldade": "medio",
      "audio_ipa": "/ˈspɔrko/"
    },
    {
      "id": "t35_078",
      "italiano": "sano",
      "portugues": "saudável",
      "genero": "m",
      "plural": "sani",
      "exemplo": "Un ambiente sano.",
      "exemplo_pt": "Um ambiente saudável.",
      "categoria": "aggettivi",
      "dificuldade": "medio",
      "audio_ipa": "/ˈsano/"
    },
    {
      "id": "t35_079",
      "italiano": "inquinato",
      "portugues": "poluído",
      "genero": "m",
      "plural": "inquinati",
      "exemplo": "Il mare è inquinato.",
      "exemplo_pt": "O mar está poluído.",
      "categoria": "aggettivi",
      "dificuldade": "medio",
      "audio_ipa": "/inkwiˈnato/"
    },
    {
      "id": "t35_080",
      "italiano": "ecologico",
      "portugues": "ecológico",
      "genero": "m",
      "plural": "ecologici",
      "exemplo": "Prodotto ecologico.",
      "exemplo_pt": "Produto ecológico.",
      "categoria": "aggettivi",
      "dificuldade": "medio",
      "audio_ipa": "/ekoˈlɔdʒiko/"
    },
    {
      "id": "t35_081",
      "italiano": "tossico",
      "portugues": "tóxico",
      "genero": "m",
      "plural": "tossici",
      "exemplo": "Gas tossico.",
      "exemplo_pt": "Gás tóxico.",
      "categoria": "aggettivi",
      "dificuldade": "medio",
      "audio_ipa": "/ˈtɔssiko/"
    },
    {
      "id": "t35_084",
      "italiano": "biodegradabile",
      "portugues": "biodegradável",
      "genero": "m",
      "plural": "biodegradabili",
      "exemplo": "Plastica biodegradabile.",
      "exemplo_pt": "Plástico biodegradável.",
      "categoria": "aggettivi",
      "dificuldade": "medio",
      "audio_ipa": "/bjodeɡraˈdabile/"
    },
    {
      "id": "t35_089",
      "italiano": "nucleare",
      "portugues": "nuclear",
      "genero": "m",
      "plural": "nucleari",
      "exemplo": "Energia nucleare.",
      "exemplo_pt": "Energia nuclear.",
      "categoria": "aggettivi",
      "dificuldade": "medio",
      "audio_ipa": "/nukleˈare/"
    },
    {
      "id": "t35_090",
      "italiano": "idroelettrico",
      "portugues": "hidrelétrico",
      "genero": "m",
      "plural": "idroelettrici",
      "exemplo": "Impianto idroelettrico.",
      "exemplo_pt": "Usina hidrelétrica.",
      "categoria": "aggettivi",
      "dificuldade": "medio",
      "audio_ipa": "/idroeˈlɛttriko/"
    },
    {
      "id": "t35_091",
      "italiano": "organico",
      "portugues": "orgânico",
      "genero": "m",
      "plural": "organici",
      "exemplo": "Rifiuto organico.",
      "exemplo_pt": "Resíduo orgânico.",
      "categoria": "aggettivi",
      "dificuldade": "medio",
      "audio_ipa": "/orˈɡaniko/"
    },
    {
      "id": "t35_092",
      "italiano": "estinto",
      "portugues": "extinto",
      "genero": "m",
      "plural": "estinti",
      "exemplo": "Animale estinto.",
      "exemplo_pt": "Animal extinto.",
      "categoria": "aggettivi",
      "dificuldade": "medio",
      "audio_ipa": "/esˈtinto/"
    },
    {
      "id": "t35_097",
      "italiano": "climatico",
      "portugues": "climático",
      "genero": "m",
      "plural": "climatici",
      "exemplo": "Cambiamento climatico.",
      "exemplo_pt": "Mudança climática.",
      "categoria": "aggettivi",
      "dificuldade": "medio",
      "audio_ipa": "/kliˈmatiko/"
    },
    {
      "id": "t35_098",
      "italiano": "ambientale",
      "portugues": "ambiental",
      "genero": "m",
      "plural": "ambientali",
      "exemplo": "Impatto ambientale.",
      "exemplo_pt": "Impacto ambiental.",
      "categoria": "aggettivi",
      "dificuldade": "medio",
      "audio_ipa": "/ambjenˈtale/"
    },
    {
      "id": "t35_099",
      "italiano": "puro",
      "portugues": "puro",
      "genero": "m",
      "plural": "puri",
      "exemplo": "Acqua pura.",
      "exemplo_pt": "Água pura.",
      "categoria": "aggettivi",
      "dificuldade": "medio",
      "audio_ipa": "/ˈpuro/"
    },
    {
      "id": "t35_100",
      "italiano": "compostaggio",
      "portugues": "compostagem",
      "genero": "m",
      "plural": "compostaggi",
      "exemplo": "Il bidone del compostaggio.",
      "exemplo_pt": "A lixeira da compostagem.",
      "categoria": "soluzioni",
      "dificuldade": "medio",
      "audio_ipa": "/komposˈtaddʒo/"
    },
    {
      "id": "t35_101",
      "italiano": "esaurimento",
      "portugues": "esgotamento",
      "genero": "m",
      "plural": "esaurimenti",
      "exemplo": "L'esaurimento delle risorse.",
      "exemplo_pt": "O esgotamento dos recursos.",
      "categoria": "problemi",
      "dificuldade": "medio",
      "audio_ipa": "/ezauriˈmento/"
    },
    {
      "id": "t35_102",
      "italiano": "idrocarburo",
      "portugues": "hidrocarboneto",
      "genero": "m",
      "plural": "idrocarburi",
      "exemplo": "L'uso di idrocarburi.",
      "exemplo_pt": "O uso de hidrocarbonetos.",
      "categoria": "problemi",
      "dificuldade": "medio",
      "audio_ipa": "/idrokarˈburo/"
    },
    {
      "id": "t35_103",
      "italiano": "petrolio",
      "portugues": "petróleo",
      "genero": "m",
      "plural": "petroli",
      "exemplo": "Estrarre il petrolio.",
      "exemplo_pt": "Extrair o petróleo.",
      "categoria": "problemi",
      "dificuldade": "medio",
      "audio_ipa": "/peˈtrɔljo/"
    },
    {
      "id": "t35_104",
      "italiano": "combustibile",
      "portugues": "combustível",
      "genero": "m",
      "plural": "combustibili",
      "exemplo": "Combustibile fossile.",
      "exemplo_pt": "Combustível fóssil.",
      "categoria": "problemi",
      "dificuldade": "medio",
      "audio_ipa": "/kombusˈtibile/"
    },
    {
      "id": "t35_105",
      "italiano": "deforestazione",
      "portugues": "desmatamento",
      "genero": "f",
      "plural": "deforestazioni",
      "exemplo": "La deforestazione avanza.",
      "exemplo_pt": "O desmatamento avança.",
      "categoria": "problemi",
      "dificuldade": "medio",
      "audio_ipa": "/deforestatˈtsjone/"
    },
    {
      "id": "t35_106",
      "italiano": "biodiversità",
      "portugues": "biodiversidade",
      "genero": "f",
      "plural": "biodiversità",
      "exemplo": "La perdita di biodiversità.",
      "exemplo_pt": "A perda de biodiversidade.",
      "categoria": "natura",
      "dificuldade": "medio",
      "audio_ipa": "/bjodiversiˈta/"
    },
    {
      "id": "t35_107",
      "italiano": "serra",
      "portugues": "estufa",
      "genero": "f",
      "plural": "serre",
      "exemplo": "L'effetto serra.",
      "exemplo_pt": "O efeito estufa.",
      "categoria": "problemi",
      "dificuldade": "medio",
      "audio_ipa": "/ˈsɛrra/"
    },
    {
      "id": "t35_108",
      "italiano": "fotovoltaico",
      "portugues": "fotovoltaico",
      "genero": "m",
      "plural": "fotovoltaici",
      "exemplo": "Impianto fotovoltaico.",
      "exemplo_pt": "Usina fotovoltaica.",
      "categoria": "soluzioni",
      "dificuldade": "medio",
      "audio_ipa": "/fotovolˈtaiko/"
    },
    {
      "id": "t35_109",
      "italiano": "termico",
      "portugues": "térmico",
      "genero": "m",
      "plural": "termici",
      "exemplo": "Inquinamento termico.",
      "exemplo_pt": "Poluição térmica.",
      "categoria": "problemi",
      "dificuldade": "medio",
      "audio_ipa": "/ˈtɛrmiko/"
    },
    {
      "id": "t35_110",
      "italiano": "ecocidio",
      "portugues": "ecocídio",
      "genero": "m",
      "plural": "ecocidi",
      "exemplo": "Un vero ecocidio.",
      "exemplo_pt": "Um verdadeiro ecocídio.",
      "categoria": "problemi",
      "dificuldade": "medio",
      "audio_ipa": "/ekoˈtʃidjo/"
    },
    {
      "id": "t35_r02",
      "italiano": "catena alimentare",
      "portugues": "cadeia alimentar",
      "genero": "f",
      "plural": "catene alimentari",
      "exemplo": "La catena alimentare collega predatori e prede.",
      "exemplo_pt": "A cadeia alimentar conecta predadores e presas.",
      "categoria": "ecologia",
      "dificuldade": "medio",
      "audio_ipa": "/kaˈteːna alimɛnˈtaːre/"
    },
    {
      "id": "t35_r03",
      "italiano": "specie a rischio",
      "portugues": "espécie em risco",
      "genero": "f",
      "plural": "specie a rischi",
      "exemplo": "Le specie a rischio vanno protette.",
      "exemplo_pt": "As espécies em risco precisam ser protegidas.",
      "categoria": "ecologia",
      "dificuldade": "medio",
      "audio_ipa": "/ˈspɛːtʃe a ˈriskjo/"
    },
    {
      "id": "t35_r05",
      "italiano": "rimboschimento",
      "portugues": "reflorestamento",
      "genero": "m",
      "plural": "rimboschimenti",
      "exemplo": "Il rimboschimento ripristina le foreste.",
      "exemplo_pt": "O reflorestamento restaura as florestas.",
      "categoria": "ecologia",
      "dificuldade": "medio",
      "audio_ipa": "/rimboˈskimento/"
    },
    {
      "id": "t35_r06",
      "italiano": "desertificazione",
      "portugues": "desertificação",
      "genero": "f",
      "plural": "desertificazioni",
      "exemplo": "La desertificazione avanza nel Sahel.",
      "exemplo_pt": "A desertificação avança no Sahel.",
      "categoria": "ecologia",
      "dificuldade": "medio",
      "audio_ipa": "/desertifikaˈttsjoːne/"
    },
    {
      "id": "t35_r07",
      "italiano": "erosione del suolo",
      "portugues": "erosão do solo",
      "genero": "f",
      "plural": "erosione del suoli",
      "exemplo": "L'erosione del suolo impoverisce la terra.",
      "exemplo_pt": "A erosão do solo empobrece a terra.",
      "categoria": "ecologia",
      "dificuldade": "medio",
      "audio_ipa": "/eroˈzjoːne del ˈswɔːlo/"
    },
    {
      "id": "t35_r08",
      "italiano": "smog fotochimico",
      "portugues": "smog fotoquímico",
      "genero": "m",
      "plural": "smog fotochimichi",
      "exemplo": "Lo smog fotochimico danneggia la salute.",
      "exemplo_pt": "O smog fotoquímico prejudica a saúde.",
      "categoria": "inquinamento",
      "dificuldade": "medio",
      "audio_ipa": "/zmɔɡ fotokˈiːmiko/"
    },
    {
      "id": "t35_r09",
      "italiano": "pioggia acida",
      "portugues": "chuva ácida",
      "genero": "f",
      "plural": "piogge acide",
      "exemplo": "La pioggia acida danneggia le foreste.",
      "exemplo_pt": "A chuva ácida prejudica as florestas.",
      "categoria": "inquinamento",
      "dificuldade": "medio",
      "audio_ipa": "/ˈpjɔddʒa ˈaːtʃida/"
    },
    {
      "id": "t35_r10",
      "italiano": "buco dell'ozono",
      "portugues": "buraco na camada de ozônio",
      "genero": "m",
      "plural": "buco dell'ozoni",
      "exemplo": "Il buco dell'ozono aumenta i raggi UV.",
      "exemplo_pt": "O buraco na camada de ozônio aumenta os raios UV.",
      "categoria": "inquinamento",
      "dificuldade": "medio",
      "audio_ipa": "/ˈbuːko delˈlɔzono/"
    },
    {
      "id": "t35_r11",
      "italiano": "riscaldamento globale",
      "portugues": "aquecimento global",
      "genero": "m",
      "plural": "riscaldamento globali",
      "exemplo": "Il riscaldamento globale scioglie i ghiacciai.",
      "exemplo_pt": "O aquecimento global derrete as geleiras.",
      "categoria": "clima",
      "dificuldade": "medio",
      "audio_ipa": "/riskaldaˈmento ɡloˈbaːle/"
    },
    {
      "id": "t35_r12",
      "italiano": "emissione di CO2",
      "portugues": "emissão de CO2",
      "genero": "f",
      "plural": "emissioni di CO2",
      "exemplo": "Le emissioni di CO2 aumentano.",
      "exemplo_pt": "As emissões de CO2 aumentam.",
      "categoria": "clima",
      "dificuldade": "medio",
      "audio_ipa": "/emisˈsjoːne di tʃiɔˈdue/"
    },
    {
      "id": "t35_r13",
      "italiano": "impronta ecologica",
      "portugues": "pegada ecológica",
      "genero": "f",
      "plural": "impronte ecologiche",
      "exemplo": "La mia impronta ecologica è alta.",
      "exemplo_pt": "Minha pegada ecológica é alta.",
      "categoria": "ecologia",
      "dificuldade": "medio",
      "audio_ipa": "/imˈprɔnta ekoˈlɔdʒika/"
    },
    {
      "id": "t35_r14",
      "italiano": "energia rinnovabile",
      "portugues": "energia renovável",
      "genero": "f",
      "plural": "energie rinnovabili",
      "exemplo": "L'energia rinnovabile è il futuro.",
      "exemplo_pt": "A energia renovável é o futuro.",
      "categoria": "energia",
      "dificuldade": "medio",
      "audio_ipa": "/eneˈrdʒiːa rinnoˈvaːbile/"
    },
    {
      "id": "t35_r18",
      "italiano": "geotermico",
      "portugues": "geotérmico",
      "genero": null,
      "plural": null,
      "exemplo": "L'energia geotermica sfrutta il calore terrestre.",
      "exemplo_pt": "A energia geotérmica usa o calor terrestre.",
      "categoria": "energia",
      "dificuldade": "medio",
      "audio_ipa": "/dʒeoˈtɛrmiko/"
    },
    {
      "id": "t35_r21",
      "italiano": "economia circolare",
      "portugues": "economia circular",
      "genero": "f",
      "plural": "economia circolari",
      "exemplo": "L'economia circolare elimina gli sprechi.",
      "exemplo_pt": "A economia circular elimina o desperdício.",
      "categoria": "ecologia",
      "dificuldade": "medio",
      "audio_ipa": "/ekoˈnɔːmja tʃirkoˈlaːre/"
    },
    {
      "id": "t35_r22",
      "italiano": "carbon footprint",
      "portugues": "pegada de carbono",
      "genero": "m",
      "plural": "carbon footprint",
      "exemplo": "Riduco il mio carbon footprint.",
      "exemplo_pt": "Reduzo minha pegada de carbono.",
      "categoria": "clima",
      "dificuldade": "medio",
      "audio_ipa": "/ˈkaːrbon ˈfutprint/"
    },
    {
      "id": "t35_r23",
      "italiano": "neutralità carbonica",
      "portugues": "neutralidade de carbono",
      "genero": "f",
      "plural": "neutralità carboniche",
      "exemplo": "L'obiettivo è la neutralità carbonica.",
      "exemplo_pt": "O objetivo é a neutralidade de carbono.",
      "categoria": "clima",
      "dificuldade": "medio",
      "audio_ipa": "/neutraliˈta karˈbɔːnika/"
    },
    {
      "id": "t35_r24",
      "italiano": "trattato climatico",
      "portugues": "tratado climático",
      "genero": "m",
      "plural": "trattati climatici",
      "exemplo": "Il trattato climatico impegna i governi.",
      "exemplo_pt": "O tratado climático compromete os governos.",
      "categoria": "politica ambientale",
      "dificuldade": "medio",
      "audio_ipa": "/tratˈtaːto klimaˈtiko/"
    },
    {
      "id": "t35_r25",
      "italiano": "accordo di Parigi",
      "portugues": "acordo de Paris",
      "genero": "m",
      "plural": "accordo di parigi",
      "exemplo": "L'accordo di Parigi fissa gli obiettivi.",
      "exemplo_pt": "O acordo de Paris define as metas.",
      "categoria": "politica ambientale",
      "dificuldade": "medio",
      "audio_ipa": "/akˈkordo di paˈriːdʒi/"
    },
    {
      "id": "t35_r26",
      "italiano": "specie invasiva",
      "portugues": "espécie invasora",
      "genero": "f",
      "plural": "specie invasive",
      "exemplo": "La specie invasiva minaccia quelle autoctone.",
      "exemplo_pt": "A espécie invasora ameaça as autóctones.",
      "categoria": "ecologia",
      "dificuldade": "medio",
      "audio_ipa": "/ˈspɛːtʃe invaˈziːva/"
    },
    {
      "id": "t35_r27",
      "italiano": "corridoio ecologico",
      "portugues": "corredor ecológico",
      "genero": "m",
      "plural": "corridoi ecologici",
      "exemplo": "Il corridoio ecologico collega gli habitat.",
      "exemplo_pt": "O corredor ecológico conecta os habitats.",
      "categoria": "ecologia",
      "dificuldade": "medio",
      "audio_ipa": "/korriˈdoːjo ekoˈlɔdʒiko/"
    },
    {
      "id": "t35_r28",
      "italiano": "parco naturale",
      "portugues": "parque natural",
      "genero": "m",
      "plural": "parchi naturali",
      "exemplo": "Il parco naturale protegge la fauna.",
      "exemplo_pt": "O parque natural protege a fauna.",
      "categoria": "protezione",
      "dificuldade": "medio",
      "audio_ipa": "/ˈparko natuˈraːle/"
    },
    {
      "id": "t35_r29",
      "italiano": "riserva naturale",
      "portugues": "reserva natural",
      "genero": "f",
      "plural": "riserve naturali",
      "exemplo": "La riserva naturale è intoccabile.",
      "exemplo_pt": "A reserva natural é intocável.",
      "categoria": "protezione",
      "dificuldade": "medio",
      "audio_ipa": "/riˈzɛrva natuˈraːle/"
    },
    {
      "id": "t35_r30",
      "italiano": "zona protetta",
      "portugues": "área protegida",
      "genero": "f",
      "plural": "zone protette",
      "exemplo": "La zona protetta vieta la caccia.",
      "exemplo_pt": "A área protegida proíbe a caça.",
      "categoria": "protezione",
      "dificuldade": "medio",
      "audio_ipa": "/ˈdzoːna proˈtetta/"
    },
    {
      "id": "t35_r32",
      "italiano": "permafrost",
      "portugues": "permafrost",
      "genero": "m",
      "plural": "permafrost",
      "exemplo": "Il permafrost si sta scongelando.",
      "exemplo_pt": "O permafrost está descongelando.",
      "categoria": "clima",
      "dificuldade": "medio",
      "audio_ipa": "/ˈpɛrmafrɔst/"
    },
    {
      "id": "t35_r33",
      "italiano": "innalzamento del mare",
      "portugues": "elevação do nível do mar",
      "genero": "m",
      "plural": "innalzamento del mari",
      "exemplo": "L'innalzamento del mare minaccia le coste.",
      "exemplo_pt": "A elevação do nível do mar ameaça as costas.",
      "categoria": "clima",
      "dificuldade": "medio",
      "audio_ipa": "/innal.ˈtsamento del ˈmaːre/"
    },
    {
      "id": "t35_r34",
      "italiano": "evento estremo",
      "portugues": "evento extremo",
      "genero": "m",
      "plural": "eventi estremi",
      "exemplo": "Gli eventi estremi aumentano col clima.",
      "exemplo_pt": "Os eventos extremos aumentam com o clima.",
      "categoria": "clima",
      "dificuldade": "medio",
      "audio_ipa": "/eˈvɛnto esˈtrɛːmo/"
    },
    {
      "id": "t35_r35",
      "italiano": "transizione energetica",
      "portugues": "transição energética",
      "genero": "f",
      "plural": "transizione energetiche",
      "exemplo": "La transizione energetica è urgente.",
      "exemplo_pt": "A transição energética é urgente.",
      "categoria": "energia",
      "dificuldade": "medio",
      "audio_ipa": "/tranziˈttsjoːne enerˈdʒɛːtika/"
    },
    {
      "id": "t35_r36",
      "italiano": "inquinamento luminoso",
      "portugues": "poluição luminosa",
      "genero": "m",
      "plural": "inquinamento luminosi",
      "exemplo": "L'inquinamento luminoso nasconde le stelle.",
      "exemplo_pt": "A poluição luminosa esconde as estrelas.",
      "categoria": "inquinamento",
      "dificuldade": "medio",
      "audio_ipa": "/inkwinaˈmento lumiˈnɔːzo/"
    },
    {
      "id": "t35_r37",
      "italiano": "inquinamento acustico",
      "portugues": "poluição sonora",
      "genero": "m",
      "plural": "inquinamento acustichi",
      "exemplo": "Il rumore è inquinamento acustico.",
      "exemplo_pt": "O ruído é poluição sonora.",
      "categoria": "inquinamento",
      "dificuldade": "medio",
      "audio_ipa": "/inkwinaˈmento aˈkuːstiko/"
    },
    {
      "id": "t35_r38",
      "italiano": "plastica usa e getta",
      "portugues": "plástico descartável",
      "genero": "f",
      "plural": "plastica usa e gette",
      "exemplo": "La plastica usa e getta va eliminata.",
      "exemplo_pt": "O plástico descartável deve ser eliminado.",
      "categoria": "riciclo",
      "dificuldade": "medio",
      "audio_ipa": "/ˈplastika ˈuːza e ˈdʒɛtta/"
    },
    {
      "id": "t35_r39",
      "italiano": "microplastica",
      "portugues": "microplástico",
      "genero": "f",
      "plural": "microplastiche",
      "exemplo": "La microplastica è ovunque.",
      "exemplo_pt": "O microplástico está em todo lugar.",
      "categoria": "inquinamento",
      "dificuldade": "medio",
      "audio_ipa": "/mikropˈlastika/"
    },
    {
      "id": "t35_r40",
      "italiano": "green economy",
      "portugues": "economia verde",
      "genero": "f",
      "plural": "green economy",
      "exemplo": "La green economy crea occupazione.",
      "exemplo_pt": "A economia verde cria empregos.",
      "categoria": "ecologia",
      "dificuldade": "medio",
      "audio_ipa": "/ˈɡriːn eˈkɔːnomi/"
    },
    {
      "id": "t35_p01",
      "italiano": "torbiera",
      "portugues": "turfeira",
      "genero": "f",
      "plural": "torbiere",
      "exemplo": "La torbiera accumula carbonio.",
      "exemplo_pt": "A turfeira acumula carbono.",
      "categoria": "natura",
      "dificuldade": "medio",
      "audio_ipa": "/torˈbjɛːra/"
    },
    {
      "id": "t35_p02",
      "italiano": "zona umida",
      "portugues": "área úmida",
      "genero": "f",
      "plural": "zone umide",
      "exemplo": "Le zone umide filtrano l'acqua.",
      "exemplo_pt": "As áreas úmidas filtram a água.",
      "categoria": "natura",
      "dificuldade": "medio",
      "audio_ipa": "/ˈdzoːna ˈuːmida/"
    },
    {
      "id": "t35_p03",
      "italiano": "barriera corallina",
      "portugues": "recife de coral",
      "genero": "f",
      "plural": "barriere coralline",
      "exemplo": "La barriera corallina è in pericolo.",
      "exemplo_pt": "O recife de coral está em perigo.",
      "categoria": "natura",
      "dificuldade": "medio",
      "audio_ipa": "/barˈrjɛːra koralˈliːna/"
    },
    {
      "id": "t35_p04",
      "italiano": "depauperamento",
      "portugues": "empobrecimento",
      "genero": "m",
      "plural": "depauperamenti",
      "exemplo": "Il depauperamento del suolo è grave.",
      "exemplo_pt": "O empobrecimento do solo é grave.",
      "categoria": "ecologia",
      "dificuldade": "medio",
      "audio_ipa": "/deˈpauperaˈmento/"
    },
    {
      "id": "t35_p05",
      "italiano": "acidificazione degli oceani",
      "portugues": "acidificação dos oceanos",
      "genero": "f",
      "plural": "acidificazione degli oceani",
      "exemplo": "L'acidificazione minaccia la vita marina.",
      "exemplo_pt": "A acidificação ameaça a vida marinha.",
      "categoria": "clima",
      "dificuldade": "medio",
      "audio_ipa": "/atʃidifikaˈttsjoːne deʎʎi otˈʃeːani/"
    },
    {
      "id": "t35_p06",
      "italiano": "ciclo dell'acqua",
      "portugues": "ciclo da água",
      "genero": "m",
      "plural": "ciclo dell'acqui",
      "exemplo": "Il ciclo dell'acqua è fondamentale.",
      "exemplo_pt": "O ciclo da água é fundamental.",
      "categoria": "ecologia",
      "dificuldade": "medio",
      "audio_ipa": "/ˈtʃiːklo dellˈakkwa/"
    },
    {
      "id": "t35_p07",
      "italiano": "ciclo del carbonio",
      "portugues": "ciclo do carbono",
      "genero": "m",
      "plural": "ciclo del carboni",
      "exemplo": "Il ciclo del carbonio regola il clima.",
      "exemplo_pt": "O ciclo do carbono regula o clima.",
      "categoria": "ecologia",
      "dificuldade": "medio",
      "audio_ipa": "/ˈtʃiːklo del karˈbɔːnjo/"
    },
    {
      "id": "t35_p09",
      "italiano": "compostabile",
      "portugues": "compostável",
      "genero": null,
      "plural": null,
      "exemplo": "L'imballaggio compostabile è ecologico.",
      "exemplo_pt": "A embalagem compostável é ecológica.",
      "categoria": "riciclo",
      "dificuldade": "medio",
      "audio_ipa": "/kompostˈaːbile/"
    },
    {
      "id": "t35_p10",
      "italiano": "risparmio energetico",
      "portugues": "economia de energia",
      "genero": "m",
      "plural": "risparmio energetichi",
      "exemplo": "Il risparmio energetico riduce le bollette.",
      "exemplo_pt": "A economia de energia reduz as contas.",
      "categoria": "energia",
      "dificuldade": "medio",
      "audio_ipa": "/risˈparmjo enerˈdʒɛːtiko/"
    },
    {
      "id": "t35_p11",
      "italiano": "efficienza energetica",
      "portugues": "eficiência energética",
      "genero": "f",
      "plural": "efficienza energetiche",
      "exemplo": "L'efficienza energetica è misurata con classe.",
      "exemplo_pt": "A eficiência energética é medida por classe.",
      "categoria": "energia",
      "dificuldade": "medio",
      "audio_ipa": "/effiˈtʃɛntsa enerˈdʒɛːtika/"
    },
    {
      "id": "t35_f01",
      "italiano": "carbon neutrality",
      "portugues": "neutralidade carbônica",
      "genero": "f",
      "plural": "carbon neutrality",
      "exemplo": "La carbon neutrality è il nostro obiettivo.",
      "exemplo_pt": "A neutralidade carbônica é nosso objetivo.",
      "categoria": "ecologia",
      "dificuldade": "medio",
      "audio_ipa": "/ˈkaːrbon njuˈtraliːti/"
    }
  ]
}