{
  "templo": 34,
  "cidade": "Providence",
  "nivel": "B1",
  "palavras": [
    {
      "id": "t34_001",
      "ingles": "ethics",
      "portugues": "ética",
      "genero": null,
      "plural": null,
      "exemplo": "Medical ethics requires doctors to always act in the patient's best interest.",
      "exemplo_pt": "A ética médica exige que os médicos ajam sempre no melhor interesse do paciente.",
      "categoria": "philosophy-ethics",
      "dificuldade": "medio",
      "audio_ipa": "/ˈeθ.ɪks/"
    },
    {
      "id": "t34_002",
      "ingles": "morality",
      "portugues": "moralidade",
      "genero": null,
      "plural": null,
      "exemplo": "People often debate whether morality is universal or culturally relative.",
      "exemplo_pt": "As pessoas frequentemente debatem se a moralidade é universal ou culturalmente relativa.",
      "categoria": "philosophy-ethics",
      "dificuldade": "medio",
      "audio_ipa": "/məˈræl.ɪ.ti/"
    },
    {
      "id": "t34_003",
      "ingles": "justice",
      "portugues": "justiça",
      "genero": null,
      "plural": null,
      "exemplo": "A fair society must ensure that justice is accessible to everyone equally.",
      "exemplo_pt": "Uma sociedade justa deve garantir que a justiça seja acessível a todos igualmente.",
      "categoria": "philosophy-ethics",
      "dificuldade": "medio",
      "audio_ipa": "/ˈdʒʌs.tɪs/"
    },
    {
      "id": "t34_004",
      "ingles": "freedom",
      "portugues": "liberdade",
      "genero": null,
      "plural": null,
      "exemplo": "Philosophers have long debated the true meaning of human freedom.",
      "exemplo_pt": "Os filósofos debatem há muito tempo o verdadeiro significado da liberdade humana.",
      "categoria": "philosophy-ethics",
      "dificuldade": "facil",
      "audio_ipa": "/ˈfriː.dəm/"
    },
    {
      "id": "t34_005",
      "ingles": "equality",
      "portugues": "igualdade",
      "genero": null,
      "plural": null,
      "exemplo": "Equality before the law is a cornerstone of modern democracies.",
      "exemplo_pt": "A igualdade perante a lei é um pilar das democracias modernas.",
      "categoria": "philosophy-ethics",
      "dificuldade": "medio",
      "audio_ipa": "/ɪˈkwɒl.ɪ.ti/"
    },
    {
      "id": "t34_006",
      "ingles": "consciousness",
      "portugues": "consciência",
      "genero": null,
      "plural": null,
      "exemplo": "The nature of consciousness is one of philosophy's most enduring mysteries.",
      "exemplo_pt": "A natureza da consciência é um dos mistérios mais duradouros da filosofia.",
      "categoria": "philosophy-ethics",
      "dificuldade": "dificil",
      "audio_ipa": "/ˈkɒn.ʃəs.nəs/"
    },
    {
      "id": "t34_007",
      "ingles": "perception",
      "portugues": "percepção",
      "genero": null,
      "plural": "perceptions",
      "exemplo": "Our perception of reality is shaped by our senses and past experiences.",
      "exemplo_pt": "Nossa percepção da realidade é moldada pelos nossos sentidos e experiências passadas.",
      "categoria": "philosophy-ethics",
      "dificuldade": "medio",
      "audio_ipa": "/pərˈsep.ʃən/"
    },
    {
      "id": "t34_008",
      "ingles": "reasoning",
      "portugues": "raciocínio",
      "genero": null,
      "plural": null,
      "exemplo": "Good reasoning helps us distinguish truth from opinion in everyday life.",
      "exemplo_pt": "Um bom raciocínio nos ajuda a distinguir a verdade da opinião na vida cotidiana.",
      "categoria": "philosophy-ethics",
      "dificuldade": "medio",
      "audio_ipa": "/ˈriː.zən.ɪŋ/"
    },
    {
      "id": "t34_009",
      "ingles": "argument",
      "portugues": "argumento",
      "genero": null,
      "plural": "arguments",
      "exemplo": "She made a strong argument in favor of reducing carbon emissions.",
      "exemplo_pt": "Ela apresentou um argumento sólido a favor da redução das emissões de carbono.",
      "categoria": "philosophy-ethics",
      "dificuldade": "medio",
      "audio_ipa": "/ˈɑːr.ɡjʊ.mənt/"
    },
    {
      "id": "t34_010",
      "ingles": "fallacy",
      "portugues": "falácia",
      "genero": null,
      "plural": "fallacies",
      "exemplo": "Blaming all problems on one group is a classic logical fallacy.",
      "exemplo_pt": "Culpar todos os problemas em um grupo é uma falácia lógica clássica.",
      "categoria": "philosophy-ethics",
      "dificuldade": "dificil",
      "audio_ipa": "/ˈfæl.ə.si/"
    },
    {
      "id": "t34_011",
      "ingles": "utilitarianism",
      "portugues": "utilitarismo",
      "genero": null,
      "plural": null,
      "exemplo": "Utilitarianism holds that the best action is the one that produces the greatest good for the greatest number.",
      "exemplo_pt": "O utilitarismo defende que a melhor ação é aquela que produz o maior bem para o maior número de pessoas.",
      "categoria": "philosophy-ethics",
      "dificuldade": "dificil",
      "audio_ipa": "/ˌjuː.tɪlˈɪˌter.i.ə.nɪ.zəm/"
    },
    {
      "id": "t34_012",
      "ingles": "empathy",
      "portugues": "empatia",
      "genero": null,
      "plural": null,
      "exemplo": "Showing empathy means understanding and sharing the feelings of another person.",
      "exemplo_pt": "Mostrar empatia significa entender e compartilhar os sentimentos de outra pessoa.",
      "categoria": "philosophy-ethics",
      "dificuldade": "medio",
      "audio_ipa": "/ˈem.pə.θi/"
    },
    {
      "id": "t34_013",
      "ingles": "virtue",
      "portugues": "virtude",
      "genero": null,
      "plural": "virtues",
      "exemplo": "Aristotle believed that virtue is developed through habit and practice.",
      "exemplo_pt": "Aristóteles acreditava que a virtude é desenvolvida por meio do hábito e da prática.",
      "categoria": "philosophy-ethics",
      "dificuldade": "medio",
      "audio_ipa": "/ˈvɜːr.tʃuː/"
    },
    {
      "id": "t34_014",
      "ingles": "integrity",
      "portugues": "integridade",
      "genero": null,
      "plural": null,
      "exemplo": "Acting with integrity means doing the right thing even when no one is watching.",
      "exemplo_pt": "Agir com integridade significa fazer a coisa certa mesmo quando ninguém está olhando.",
      "categoria": "philosophy-ethics",
      "dificuldade": "medio",
      "audio_ipa": "/ɪnˈteɡ.rɪ.ti/"
    },
    {
      "id": "t34_015",
      "ingles": "dilemma",
      "portugues": "dilema",
      "genero": null,
      "plural": "dilemmas",
      "exemplo": "The trolley problem is a famous ethical dilemma in philosophy.",
      "exemplo_pt": "O problema do bonde é um famoso dilema ético na filosofia.",
      "categoria": "philosophy-ethics",
      "dificuldade": "medio",
      "audio_ipa": "/dɪˈlem.ə/"
    },
    {
      "id": "t34_016",
      "ingles": "bias",
      "portugues": "viés / preconceito inconsciente",
      "genero": null,
      "plural": "biases",
      "exemplo": "We all have unconscious biases that can influence how we treat others.",
      "exemplo_pt": "Todos nós temos preconceitos inconscientes que podem influenciar como tratamos os outros.",
      "categoria": "philosophy-ethics",
      "dificuldade": "medio",
      "audio_ipa": "/ˈbaɪ.əs/"
    },
    {
      "id": "t34_017",
      "ingles": "prejudice",
      "portugues": "preconceito",
      "genero": null,
      "plural": "prejudices",
      "exemplo": "Prejudice often stems from a lack of exposure to different cultures or ideas.",
      "exemplo_pt": "O preconceito frequentemente surge da falta de contato com diferentes culturas ou ideias.",
      "categoria": "philosophy-ethics",
      "dificuldade": "medio",
      "audio_ipa": "/ˈpredʒ.ʊ.dɪs/"
    },
    {
      "id": "t34_018",
      "ingles": "perspective",
      "portugues": "perspectiva / ponto de vista",
      "genero": null,
      "plural": "perspectives",
      "exemplo": "Considering multiple perspectives helps us make more balanced decisions.",
      "exemplo_pt": "Considerar múltiplas perspectivas nos ajuda a tomar decisões mais equilibradas.",
      "categoria": "philosophy-ethics",
      "dificuldade": "medio",
      "audio_ipa": "/pərˈspek.tɪv/"
    },
    {
      "id": "t34_019",
      "ingles": "critical thinking",
      "portugues": "pensamento crítico",
      "genero": null,
      "plural": null,
      "exemplo": "Critical thinking is the ability to analyze information objectively before forming a conclusion.",
      "exemplo_pt": "O pensamento crítico é a capacidade de analisar informações objetivamente antes de formar uma conclusão.",
      "categoria": "philosophy-ethics",
      "dificuldade": "medio",
      "audio_ipa": "/ˈkrɪt.ɪ.kəl ˈθɪŋ.kɪŋ/"
    },
    {
      "id": "t34_020",
      "ingles": "paradox",
      "portugues": "paradoxo",
      "genero": null,
      "plural": "paradoxes",
      "exemplo": "The statement 'this sentence is false' is a classic philosophical paradox.",
      "exemplo_pt": "A afirmação 'esta frase é falsa' é um paradoxo filosófico clássico.",
      "categoria": "philosophy-ethics",
      "dificuldade": "dificil",
      "audio_ipa": "/ˈpær.ə.dɒks/"
    }
  ],
  "quizzes": [
    {
      "pergunta": "What is utilitarianism?",
      "opcoes": ["A philosophy focused on individual rights above all else", "The belief that actions are right if they produce the greatest good for the greatest number", "A philosophy that values tradition and virtue", "The view that morality is completely subjective"],
      "resposta": 1,
      "explicacao": "Utilitarianism, associated with philosophers like Bentham and Mill, judges actions by their outcomes — the best action produces the most overall happiness."
    },
    {
      "pergunta": "What is a 'fallacy' in logical reasoning?",
      "opcoes": ["A well-supported conclusion", "A type of philosophical thought experiment", "An error in reasoning that makes an argument invalid", "A synonym for a paradox"],
      "resposta": 2,
      "explicacao": "A fallacy is a flaw or error in logical reasoning. Fallacies can be formal (structural errors) or informal (errors in content or context)."
    },
    {
      "pergunta": "What does 'empathy' mean?",
      "opcoes": ["Judging others based on their actions", "The ability to understand and share the feelings of others", "The practice of self-reflection", "Treating all people with strict fairness"],
      "resposta": 1,
      "explicacao": "Empathy is the capacity to understand and emotionally connect with what another person is experiencing, seeing things from their point of view."
    },
    {
      "pergunta": "What is a 'paradox'?",
      "opcoes": ["A type of logical fallacy involving hasty conclusions", "A statement that seems self-contradictory but may reveal a deeper truth", "A virtue described by Aristotle", "A bias that affects decision-making"],
      "resposta": 1,
      "explicacao": "A paradox is a statement or situation that appears contradictory yet may be logically valid or point to a profound truth."
    },
    {
      "pergunta": "What does 'integrity' mean in an ethical context?",
      "opcoes": ["Being critical of others' actions", "Holding strong opinions regardless of evidence", "Acting honestly and morally even without oversight", "Applying utilitarian principles to decision-making"],
      "resposta": 2,
      "explicacao": "Integrity means adhering to moral principles consistently — doing what is right not because you have to, but because it aligns with your values."
    }
  ]
}