{
  "templo": 12,
  "cidade": "Seattle",
  "nivel": "A2",
  "palavras": [
    {
      "id": "t12_001",
      "italiano": "weather",
      "portugues": "tempo (clima)",
      "genero": null,
      "plural": null,
      "exemplo": "The weather in Seattle is often cloudy and rainy.",
      "exemplo_pt": "O tempo em Seattle é frequentemente nublado e chuvoso.",
      "categoria": "weather",
      "dificuldade": "facil",
      "audio_ipa": "/ˈwɛðər/"
    },
    {
      "id": "t12_002",
      "italiano": "sunny",
      "portugues": "ensolarado",
      "genero": null,
      "plural": null,
      "exemplo": "It's a beautiful, sunny day — let's go to the park!",
      "exemplo_pt": "É um lindo dia ensolarado — vamos ao parque!",
      "categoria": "weather",
      "dificuldade": "facil",
      "audio_ipa": "/ˈsʌni/"
    },
    {
      "id": "t12_003",
      "italiano": "cloudy",
      "portugues": "nublado",
      "genero": null,
      "plural": null,
      "exemplo": "It's been cloudy all week and I miss the sunshine.",
      "exemplo_pt": "Está nublado a semana toda e eu sinto falta do sol.",
      "categoria": "weather",
      "dificuldade": "facil",
      "audio_ipa": "/ˈklaʊdi/"
    },
    {
      "id": "t12_004",
      "italiano": "rainy",
      "portugues": "chuvoso",
      "genero": null,
      "plural": null,
      "exemplo": "Bring your umbrella — it's going to be a rainy afternoon.",
      "exemplo_pt": "Traga seu guarda-chuva — vai ser uma tarde chuvosa.",
      "categoria": "weather",
      "dificuldade": "facil",
      "audio_ipa": "/ˈreɪni/"
    },
    {
      "id": "t12_005",
      "italiano": "windy",
      "portugues": "ventoso / com vento",
      "genero": null,
      "plural": null,
      "exemplo": "It's so windy outside that my hat flew off!",
      "exemplo_pt": "Está tão ventoso lá fora que meu chapéu voou!",
      "categoria": "weather",
      "dificuldade": "facil",
      "audio_ipa": "/ˈwɪndi/"
    },
    {
      "id": "t12_006",
      "italiano": "hot",
      "portugues": "quente",
      "genero": null,
      "plural": null,
      "exemplo": "It's way too hot to go jogging today — it must be 100°F.",
      "exemplo_pt": "Está quente demais para correr hoje — deve estar uns 38°C.",
      "categoria": "weather",
      "dificuldade": "facil",
      "audio_ipa": "/hɒt/"
    },
    {
      "id": "t12_007",
      "italiano": "cold",
      "portugues": "frio",
      "genero": null,
      "plural": null,
      "exemplo": "It's so cold this morning — I can see my breath!",
      "exemplo_pt": "Está tão frio esta manhã — consigo ver meu hálito!",
      "categoria": "weather",
      "dificuldade": "facil",
      "audio_ipa": "/koʊld/"
    },
    {
      "id": "t12_008",
      "italiano": "warm",
      "portugues": "morno / agradavelmente quente",
      "genero": null,
      "plural": null,
      "exemplo": "The weather is warm and pleasant — perfect for a picnic.",
      "exemplo_pt": "O tempo está morno e agradável — perfeito para um piquenique.",
      "categoria": "weather",
      "dificuldade": "facil",
      "audio_ipa": "/wɔːrm/"
    },
    {
      "id": "t12_009",
      "italiano": "cool",
      "portugues": "fresco",
      "genero": null,
      "plural": null,
      "exemplo": "The evening air is cool, so grab a light jacket.",
      "exemplo_pt": "O ar da noite está fresco, então pegue uma jaqueta leve.",
      "categoria": "weather",
      "dificuldade": "facil",
      "audio_ipa": "/kuːl/"
    },
    {
      "id": "t12_010",
      "italiano": "snow",
      "portugues": "neve",
      "genero": null,
      "plural": null,
      "exemplo": "The kids were excited to see snow for the first time.",
      "exemplo_pt": "As crianças ficaram animadas ao ver neve pela primeira vez.",
      "categoria": "weather",
      "dificuldade": "facil",
      "audio_ipa": "/snoʊ/"
    },
    {
      "id": "t12_011",
      "italiano": "storm",
      "portugues": "tempestade",
      "genero": null,
      "plural": "storms",
      "exemplo": "A big storm is coming tonight — stay indoors if you can.",
      "exemplo_pt": "Uma grande tempestade está chegando esta noite — fique em casa se puder.",
      "categoria": "weather",
      "dificuldade": "facil",
      "audio_ipa": "/stɔːrm/"
    },
    {
      "id": "t12_012",
      "italiano": "forecast",
      "portugues": "previsão do tempo",
      "genero": null,
      "plural": "forecasts",
      "exemplo": "According to the forecast, it will rain all weekend.",
      "exemplo_pt": "De acordo com a previsão do tempo, vai chover o fim de semana todo.",
      "categoria": "weather",
      "dificuldade": "medio",
      "audio_ipa": "/ˈfɔːrkæst/"
    },
    {
      "id": "t12_013",
      "italiano": "temperature",
      "portugues": "temperatura",
      "genero": null,
      "plural": "temperatures",
      "exemplo": "The temperature dropped to 28°F last night — it was freezing!",
      "exemplo_pt": "A temperatura caiu para -2°C ontem à noite — estava congelando!",
      "categoria": "weather",
      "dificuldade": "medio",
      "audio_ipa": "/ˈtɛmprətʃər/"
    },
    {
      "id": "t12_014",
      "italiano": "season",
      "portugues": "estação (do ano)",
      "genero": null,
      "plural": "seasons",
      "exemplo": "My favorite season is fall because of the colorful leaves.",
      "exemplo_pt": "Minha estação favorita é o outono por causa das folhas coloridas.",
      "categoria": "nature",
      "dificuldade": "facil",
      "audio_ipa": "/ˈsiːzən/"
    },
    {
      "id": "t12_015",
      "italiano": "spring",
      "portugues": "primavera",
      "genero": null,
      "plural": null,
      "exemplo": "Flowers bloom everywhere in spring.",
      "exemplo_pt": "Flores desabrocham por toda parte na primavera.",
      "categoria": "nature",
      "dificuldade": "facil",
      "audio_ipa": "/sprɪŋ/"
    },
    {
      "id": "t12_016",
      "italiano": "summer",
      "portugues": "verão",
      "genero": null,
      "plural": null,
      "exemplo": "We go to the beach every summer as a family tradition.",
      "exemplo_pt": "Vamos à praia todo verão como tradição familiar.",
      "categoria": "nature",
      "dificuldade": "facil",
      "audio_ipa": "/ˈsʌmər/"
    },
    {
      "id": "t12_017",
      "italiano": "fall",
      "portugues": "outono",
      "genero": null,
      "plural": null,
      "exemplo": "The leaves turn red and orange in the fall.",
      "exemplo_pt": "As folhas ficam vermelhas e laranja no outono.",
      "categoria": "nature",
      "dificuldade": "facil",
      "audio_ipa": "/fɔːl/"
    },
    {
      "id": "t12_018",
      "italiano": "winter",
      "portugues": "inverno",
      "genero": null,
      "plural": null,
      "exemplo": "Winter in Seattle is mild but very rainy.",
      "exemplo_pt": "O inverno em Seattle é ameno, mas muito chuvoso.",
      "categoria": "nature",
      "dificuldade": "facil",
      "audio_ipa": "/ˈwɪntər/"
    },
    {
      "id": "t12_019",
      "italiano": "umbrella",
      "portugues": "guarda-chuva",
      "genero": null,
      "plural": "umbrellas",
      "exemplo": "I always keep an umbrella in my bag when it looks cloudy.",
      "exemplo_pt": "Sempre carrego um guarda-chuva na bolsa quando parece nublado.",
      "categoria": "weather",
      "dificuldade": "medio",
      "audio_ipa": "/ʌmˈbrɛlə/"
    },
    {
      "id": "t12_020",
      "italiano": "coat",
      "portugues": "casaco",
      "genero": null,
      "plural": "coats",
      "exemplo": "You'll definitely need a warm coat in January here.",
      "exemplo_pt": "Você vai precisar definitivamente de um casaco quente em janeiro aqui.",
      "categoria": "weather",
      "dificuldade": "facil",
      "audio_ipa": "/koʊt/"
    }
  ],
  "quizzes": [
    {
      "pergunta": "What is a 'forecast'?",
      "opcoes": ["A type of storm", "A weather prediction for the coming days", "A warm season", "A kind of umbrella"],
      "resposta": 1,
      "explicacao": "A 'forecast' is a prediction of future weather conditions, often given by meteorologists on TV or weather apps."
    },
    {
      "pergunta": "Which word describes weather that is neither hot nor cold, but pleasantly warm?",
      "opcoes": ["Windy", "Stormy", "Cool", "Warm"],
      "resposta": 3,
      "explicacao": "'Warm' describes a comfortable, pleasantly high temperature — not as extreme as 'hot'. 'Cool' means slightly cold."
    },
    {
      "pergunta": "In the US, 'fall' refers to which season?",
      "opcoes": ["Spring", "Summer", "Autumn", "Winter"],
      "resposta": 2,
      "explicacao": "'Fall' is the American English word for 'autumn' — the season between summer and winter when leaves change color and drop."
    },
    {
      "pergunta": "Which item would you use to protect yourself from rain?",
      "opcoes": ["Coat", "Umbrella", "Storm", "Forecast"],
      "resposta": 1,
      "explicacao": "An 'umbrella' is a handheld canopy that protects you from rain. A coat protects from cold but not specifically from rain."
    },
    {
      "pergunta": "What is the correct order of the four seasons?",
      "opcoes": ["Summer, fall, winter, spring", "Spring, winter, fall, summer", "Winter, summer, spring, fall", "Fall, summer, winter, spring"],
      "resposta": 0,
      "explicacao": "The four seasons in order are: spring → summer → fall (autumn) → winter, then back to spring again."
    }
  ]
}